odoo8_addon_product_harmonized_system-8.0.0.2.0.99.dev7-py2.7-nspkg.pth
odoo8_addon_product_harmonized_system-8.0.0.2.0.99.dev7.dist-info/METADATA
odoo8_addon_product_harmonized_system-8.0.0.2.0.99.dev7.dist-info/RECORD
odoo8_addon_product_harmonized_system-8.0.0.2.0.99.dev7.dist-info/WHEEL
odoo8_addon_product_harmonized_system-8.0.0.2.0.99.dev7.dist-info/namespace_packages.txt
odoo8_addon_product_harmonized_system-8.0.0.2.0.99.dev7.dist-info/top_level.txt
odoo_addons/product_harmonized_system/README.rst
odoo_addons/product_harmonized_system/__init__.py
odoo_addons/product_harmonized_system/__openerp__.py
odoo_addons/product_harmonized_system/demo/product_demo.xml
odoo_addons/product_harmonized_system/i18n/fr.po
odoo_addons/product_harmonized_system/i18n/product_harmonized_system.pot
odoo_addons/product_harmonized_system/models/__init__.py
odoo_addons/product_harmonized_system/models/hs_code.py
odoo_addons/product_harmonized_system/models/product_category.py
odoo_addons/product_harmonized_system/models/product_template.py
odoo_addons/product_harmonized_system/security/ir.model.access.csv
odoo_addons/product_harmonized_system/security/product_hs_security.xml
odoo_addons/product_harmonized_system/static/description/icon.png
odoo_addons/product_harmonized_system/views/hs_code.xml
odoo_addons/product_harmonized_system/views/product_category.xml
odoo_addons/product_harmonized_system/views/product_template.xml
