Metadata-Version: 2.1
Name: odoo8-addon-product-harmonized-system
Version: 8.0.0.2.0.99.dev7
Summary: Base module for Product Import/Export reports
Home-page: UNKNOWN
Author: Akretion, Noviat, Odoo Community Association (OCA)
Author-email: support@odoo-community.org
License: AGPL-3
Platform: UNKNOWN
Classifier: Programming Language :: Python
Classifier: Framework :: Odoo
Classifier: License :: OSI Approved :: GNU Affero General Public License v3
Requires-Python: ~=2.7
Requires-Dist: odoo (<9.0a,>=8.0a)
